tvtui.py
tvtui-2.0.0.dist-info/METADATA
tvtui-2.0.0.dist-info/WHEEL
tvtui-2.0.0.dist-info/entry_points.txt
tvtui-2.0.0.dist-info/top_level.txt
tvtui-2.0.0.dist-info/RECORD
