Metadata-Version: 2.4
Name: tvtui
Version: 2.0.0
Summary: Terminal UI for IPTV with EPG browsing
Author: tvTUI Contributors
License: MIT
Keywords: tui,iptv,epg,terminal
Classifier: Environment :: Console
Classifier: Intended Audience :: End Users/Desktop
Classifier: License :: OSI Approved :: MIT License
Classifier: Programming Language :: Python :: 3
Classifier: Programming Language :: Python :: 3 :: Only
Classifier: Topic :: Multimedia :: Video
Classifier: Topic :: Utilities
Requires-Python: >=3.9
